sendwithus/__init__.py
sendwithus/encoder.py
sendwithus/exceptions.py
sendwithus/version.py
sendwithus-5.4.0.dist-info/licenses/LICENSE
sendwithus-5.4.0.dist-info/licenses/NOTICE
sendwithus-5.4.0.dist-info/METADATA
sendwithus-5.4.0.dist-info/WHEEL
sendwithus-5.4.0.dist-info/top_level.txt
sendwithus-5.4.0.dist-info/RECORD
