Metadata-Version: 2.4
Name: sendwithus
Version: 5.4.0
Summary: Python API client for sendwithus.com
Home-page: https://github.com/sendwithus/sendwithus_python
Author: sendwithus
Author-email: us@sendwithus.com
License: LICENSE.txt
Classifier: Programming Language :: Python :: 2
Classifier: Programming Language :: Python :: 2.7
Classifier: Programming Language :: Python :: 3
Classifier: Programming Language :: Python :: 3.4
Classifier: Programming Language :: Python :: 3.5
Classifier: License :: OSI Approved :: Apache Software License
Classifier: Development Status :: 5 - Production/Stable
Classifier: Topic :: Communications :: Email
License-File: LICENSE
License-File: NOTICE
Requires-Dist: requests>=2.0.0
Requires-Dist: six>=1.9.0
Provides-Extra: test
Requires-Dist: pytest>=3.0.5; extra == "test"
Requires-Dist: pytest-xdist>=1.15.0; extra == "test"
Dynamic: author
Dynamic: author-email
Dynamic: classifier
Dynamic: description
Dynamic: description-content-type
Dynamic: home-page
Dynamic: license
Dynamic: license-file
Dynamic: provides-extra
Dynamic: requires-dist
Dynamic: summary
